chemomae/__init__.py
chemomae/_version.py
chemomae/py.typed
chemomae/clustering/__init__.py
chemomae/clustering/cosine_kmeans.py
chemomae/clustering/metric.py
chemomae/clustering/ops.py
chemomae/clustering/vmf_mixture.py
chemomae/models/__init__.py
chemomae/models/chemo_mae.py
chemomae/models/losses.py
chemomae/preprocessing/__init__.py
chemomae/preprocessing/downsampling.py
chemomae/preprocessing/snv.py
chemomae/training/__init__.py
chemomae/training/callbacks.py
chemomae/training/extractor.py
chemomae/training/optim.py
chemomae/training/tester.py
chemomae/training/trainer.py
chemomae/utils/__init__.py
chemomae/utils/seed.py
chemomae-0.1.6.dist-info/licenses/LICENSE
chemomae-0.1.6.dist-info/licenses/NOTICE
chemomae-0.1.6.dist-info/METADATA
chemomae-0.1.6.dist-info/WHEEL
chemomae-0.1.6.dist-info/top_level.txt
chemomae-0.1.6.dist-info/RECORD
