Metadata-Version: 2.4
Name: chemomae
Version: 0.1.6
Summary: ChemoMAE: 1D Spectral Masked Autoencoder + Hyperspherical Clustering Toolkit
Author: Ryuji Yamaguchi
License:                                  Apache License
Project-URL: Homepage, https://github.com/Mantis-Ryuji/ChemoMAE
Project-URL: Documentation, https://github.com/Mantis-Ryuji/ChemoMAE/blob/main/README.md
Project-URL: Issues, https://github.com/Mantis-Ryuji/ChemoMAE/issues
Keywords: spectroscopy,hyperspectral,masked autoencoder,self-supervised,unsupervised,representation learning,clustering,cosine similarity,kmeans
Classifier: Development Status :: 3 - Alpha
Classifier: Intended Audience :: Science/Research
Classifier: License :: OSI Approved :: Apache Software License
Classifier: Operating System :: OS Independent
Classifier: Programming Language :: Python
Classifier: Programming Language :: Python :: 3
Classifier: Programming Language :: Python :: 3 :: Only
Classifier: Programming Language :: Python :: 3.9
Classifier: Programming Language :: Python :: 3.10
Classifier: Programming Language :: Python :: 3.11
Classifier: Programming Language :: Python :: 3.12
Classifier: Topic :: Scientific/Engineering
Classifier: Topic :: Scientific/Engineering :: Artificial Intelligence
Classifier: Topic :: Scientific/Engineering :: Information Analysis
Classifier: Topic :: Scientific/Engineering :: Image Recognition
Requires-Python: >=3.9
License-File: LICENSE
License-File: NOTICE
Requires-Dist: packaging>=23.1
Requires-Dist: numpy>=1.24
Requires-Dist: scipy>=1.10
Requires-Dist: tqdm>=4.66
Requires-Dist: matplotlib>=3.8
Requires-Dist: pyyaml>=6.0
Provides-Extra: dev
Requires-Dist: pytest<9,>=7; extra == "dev"
Requires-Dist: ruff>=0.4; extra == "dev"
Requires-Dist: mypy>=1.7; extra == "dev"
Requires-Dist: build>=1.2; extra == "dev"
Requires-Dist: twine>=5; extra == "dev"
Requires-Dist: scikit-learn<1.6,>=1.2; extra == "dev"
Requires-Dist: torch>=2.1; extra == "dev"
Dynamic: license-file
